pyproject.toml
README.md
register_code_gen/__init__.py
register_code_gen/register_code_gen.py
register_code_gen-0.2.0.dist-info/entry_points.txt
register_code_gen-0.2.0.dist-info/LICENSE
register_code_gen-0.2.0.dist-info/license.rtf
register_code_gen-0.2.0.dist-info/METADATA
register_code_gen-0.2.0.dist-info/WHEEL
register_code_gen-0.2.0.dist-info/RECORD
