Metadata-Version: 2.1
Name: register-code-gen
Version: 0.2.0
Summary: Generate code for registers based on SVD files
Home-page: https://github.com/drbartling/register_code_gen
Author: Ryan Bartling
Author-email: ryan.bartling@gmail.com
Requires-Python: >=3.10,<3.12
Classifier: Programming Language :: Python :: 3
Classifier: Programming Language :: Python :: 3.10
Classifier: Programming Language :: Python :: 3.11
Requires-Dist: click (>=8.1.3,<9.0.0)
Requires-Dist: pydantic (>=2.3.0,<3.0.0)
Requires-Dist: rich (>=13.5.2,<14.0.0)
Requires-Dist: xmltodict (>=0.13.0,<0.14.0)
Project-URL: Repository, https://github.com/drbartling/register_code_gen
